{
	"300800": [
		
	],
	"300117": [
		
	],
	"300118": [
		
	],
	"300120": [
		
	],
	"300119": [
		
	],
	"300801": [
		
	],
	"300912": [
		
	],
	"300913": [
		
	],
	"301004": [
		
	],
	"301005": [
		
	],
	"301006": [
		
	],
	"301007": [
		
	],
	"301008": [
		
	],
	"301009": [
		
	],
	"301010": [
		
	],
	"301011": [
		
	],
	"301012": [
		
	],
	"301013": [
		
	],
	"301014": [
		
	],
	"301015": [
		
	],
	"301016": [
		
	],
	"301017": [
		
	],
	"301028": [
		
	],
	"301029": [
		
	],
	"301030": [
		
	],
	"301031": [
		
	],
	"301032": [
		
	],
	"301033": [
		
	],
	"301034": [
		
	],
	"301035": [
		
	],
	"301018": [
		
	],
	"301019": [
		
	],
	"301020": [
		
	],
	"301021": [
		
	],
	"301022": [
		
	],
	"301023": [
		
	],
	"301024": [
		
	],
	"301025": [
		
	],
	"301026": [
		
	],
	"301027": [
		
	],
	"300962": [
		
	],
	"300964": [
		
	],
	"300914": [
		
	],
	"300916": [
		
	],
	"300915": [
		
	],
	"300810": [
		
	],
	"300812": [
		
	],
	"300813": [
		
	],
	"300814": [
		
	],
	"300815": [
		
	],
	"301042": [
		
	],
	"300811": [
		
	],
	"300965": [
		
	],
	"301044": [
		
	],
	"300802": [
		
	],
	"300973": [
		
	],
	"300974": [
		
	],
	"300975": [
		
	],
	"300976": [
		
	],
	"300977": [
		
	],
	"300978": [
		
	],
	"300979": [
		
	],
	"300980": [
		
	],
	"300981": [
		
	],
	"300982": [
		
	],
	"300983": [
		
	],
	"300919": [
		
	],
	"300984": [
		
	],
	"300995": [
		
	],
	"300996": [
		
	],
	"300997": [
		
	],
	"300998": [
		
	],
	"300999": [
		
	],
	"301000": [
		
	],
	"301001": [
		
	],
	"301002": [
		
	],
	"300985": [
		
	],
	"300986": [
		
	],
	"300987": [
		
	],
	"300988": [
		
	],
	"300989": [
		
	],
	"300990": [
		
	],
	"300991": [
		
	],
	"300992": [
		
	],
	"300993": [
		
	],
	"300994": [
		
	],
	"301047": [
		
	],
	"300790": [
		
	],
	"300791": [
		
	],
	"300809": [
		
	],
	"300797": [
		
	],
	"300792": [
		
	],
	"300111": [
		
	],
	"300112": [
		
	],
	"300121": [
		
	],
	"300649": [
		
	],
	"300122": [
		
	],
	"300149": [
		
	],
	"300113": [
		
	],
	"300127": [
		
	],
	"300132": [
		
	],
	"300129": [
		
	],
	"300115": [
		
	],
	"300116": [
		
	],
	"300114": [
		
	],
	"300110": [
		
	]
}